LICENSE
README.md
giup/__init__.py
giup/cli.py
giup/command.py
giup/git.py
giup/project.py
giup/util.py
giup-1.1.6.dist-info/LICENSE
giup-1.1.6.dist-info/METADATA
giup-1.1.6.dist-info/WHEEL
giup-1.1.6.dist-info/entry_points.txt
giup-1.1.6.dist-info/RECORD
