Metadata-Version: 2.1
Name: giup
Version: 1.1.6
Summary: Interactively and hierarchically perform git merges across branches and run commands in between.
Home-page: https://github.com/Siphalor/giup
License: Apache-2.0
Author: Siphalor
Author-email: info@siphalor.de
Requires-Python: >=3.8,<4.0
Classifier: License :: OSI Approved :: Apache Software License
Classifier: Natural Language :: English
Classifier: Programming Language :: Python
Classifier: Programming Language :: Python :: 3
Classifier: Programming Language :: Python :: 3.8
Classifier: Programming Language :: Python :: 3.9
Classifier: Programming Language :: Python :: 3.10
Classifier: Programming Language :: Python :: 3.11
Classifier: Programming Language :: Python :: 3
Classifier: Programming Language :: Python :: 3.6
Classifier: Programming Language :: Python :: Implementation :: CPython
Classifier: Programming Language :: Python :: Implementation :: PyPy
Classifier: Topic :: Software Development :: Build Tools
Classifier: Topic :: Software Development :: Version Control :: Git
Requires-Dist: termcolor (>=2.3.0,<3.0.0)
Project-URL: Repository, https://github.com/Siphalor/giup
